{
  "status": "tasks_created",
  "summary": "Created 4 tasks to fix --lit flag workflow for CSLib extension: sub-index creation (#760), skill wiring (#761), agent injection (#762), and integration test (#763).",
  "artifacts": [
    {
      "type": "task_entry",
      "path": "specs/TODO.md",
      "summary": "Tasks #760-763 added to TODO.md with diamond dependency graph"
    }
  ],
  "metadata": {
    "session_id": "sess_meta_lit_fix",
    "duration_seconds": 120,
    "agent_type": "meta-builder-agent",
    "delegation_depth": 2,
    "delegation_path": ["orchestrator", "meta", "skill-meta", "meta-builder-agent"],
    "mode": "prompt",
    "tasks_created": 4
  },
  "next_steps": "Run /research 760 to begin research on foundational task (create literature sub-index)"
}
