{
  "status": "planned",
  "summary": "Created 3-phase plan: Phase 1 adds project detection and Tier 2 filtering to literature-retrieve.sh, Phase 2 adds --project flag to literature-search.sh for Tier 1 FTS5 filtering, Phase 3 runs integration tests and edge case verification.",
  "blockers": [],
  "continuation_context": null,
  "next_action_hint": "implement",
  "phases_completed": 0,
  "phases_total": 3,
  "artifacts": [
    {
      "path": "specs/735_literature_project_aware_filtering/plans/01_project-aware-filtering.md",
      "type": "plan",
      "summary": "Implementation plan for project-aware literature filtering"
    }
  ]
}
